{
  "generator-cg-angular": {
    "uirouter": true,
    "partialDirectory": "lessons/",
    "directiveDirectory": "directives/",
    "filterDirectory": "filters/",
    "serviceDirectory": "services/",
    "inject": {
      "js": {
        "file": "index.html",
        "marker": "<!-- Add New Component JS Above -->",
        "template": "<script src=\"<%= filename %>\"></script>"
      },
      "less": {
        "relativeToModule": true,
        "file": "<%= module %>.less",
        "marker": "/* Add Component LESS Above */",
        "template": "@import \"<%= filename %>\";"
      }
    },
    "modules": [
      {
        "name": "openWeatherApp",
        "file": "lessons\\unit-2\\open-weather-app\\open-weather-app.js"
      },
      {
        "name": "countriesCapitals",
        "file": "lessons\\unit-2\\countries-capitals\\countries-capitals.js"
      }
    ]
  }
}